sogs/__init__.py
sogs/cli.py
sogs/sogs_compression.py
sogs-1.0.0.dist-info/METADATA
sogs-1.0.0.dist-info/WHEEL
sogs-1.0.0.dist-info/entry_points.txt
sogs-1.0.0.dist-info/licenses/LICENSE
sogs-1.0.0.dist-info/RECORD
