Metadata-Version: 2.4
Name: sogs
Version: 1.0.0
Summary: Standalone compression tool for gaussian splat .plys
Project-URL: Homepage, https://github.com/vincentwoo/SOGS/
Author-email: Vincent Woo <me@vincentwoo.com>
License:                                  Apache License
License-File: LICENSE
Requires-Python: >=3.8
Requires-Dist: numpy
Requires-Dist: pillow
Requires-Dist: plyfile
Requires-Dist: tyro
